<?xml version="1.0" encoding="UTF-8"?>
<beans xmlns="http://www.springframework.org/schema/beans"
       xmlns:xsi="http://www.w3.org/2001/XMLSchema-instance"
       xmlns:context="http://www.springframework.org/schema/context"
       xmlns:util="http://www.springframework.org/schema/util"
       xsi:schemaLocation="http://www.springframework.org/schema/beans http://www.springframework.org/schema/beans/spring-beans.xsd
       http://www.springframework.org/schema/context http://www.springframework.org/schema/context/spring-context.xsd http://www.springframework.org/schema/util http://www.springframework.org/schema/util/spring-util.xsd">



  <bean name="server" id="jolokia" class="org.jolokia.jvmagent.spring.SpringJolokiaAgent">
    <property name="config">
      <bean class="org.jolokia.jvmagent.spring.SpringJolokiaConfigHolder">
        <property name="config">
          <util:map>
            <entry key="autoStart" value="true"/>
            <entry key="host" value="127.0.0.1"/>
            <entry key="port" value="${jmx.jolokiaPort}"/>
            <entry key="agentContext" value="/jolokia"/>
          </util:map>
        </property>
      </bean>
    </property>
  </bean>
</beans>